brady-django-template/__init__.py
brady-django-template/main.py
brady_django_template/__init__.py
brady_django_template/main.py
brady_django_template/project-template/Procfile
brady_django_template/project-template/README.md
brady_django_template/project-template/manage.py
brady_django_template/project-template/requirements.txt
brady_django_template/project-template/runtime.txt
brady_django_template/project-template/app_auth/__init__.py
brady_django_template/project-template/app_auth/admin.py
brady_django_template/project-template/app_auth/apps.py
brady_django_template/project-template/app_auth/managers.py
brady_django_template/project-template/app_auth/models.py
brady_django_template/project-template/app_auth/otp_views.py
brady_django_template/project-template/app_auth/serializers.py
brady_django_template/project-template/app_auth/tests.py
brady_django_template/project-template/app_auth/urls.py
brady_django_template/project-template/app_auth/views.py
brady_django_template/project-template/app_auth/__pycache__/__init__.cpython-311.pyc
brady_django_template/project-template/app_auth/__pycache__/admin.cpython-311.pyc
brady_django_template/project-template/app_auth/__pycache__/apps.cpython-311.pyc
brady_django_template/project-template/app_auth/__pycache__/managers.cpython-311.pyc
brady_django_template/project-template/app_auth/__pycache__/models.cpython-311.pyc
brady_django_template/project-template/app_auth/__pycache__/otp_views.cpython-311.pyc
brady_django_template/project-template/app_auth/__pycache__/serializers.cpython-311.pyc
brady_django_template/project-template/app_auth/__pycache__/urls.cpython-311.pyc
brady_django_template/project-template/app_auth/__pycache__/views.cpython-311.pyc
brady_django_template/project-template/app_auth/migrations/__init__.py
brady_django_template/project-template/app_auth/migrations/__pycache__/0001_initial.cpython-311.pyc
brady_django_template-0.1.4.dist-info/LICENSE
brady_django_template-0.1.4.dist-info/METADATA
brady_django_template-0.1.4.dist-info/WHEEL
brady_django_template-0.1.4.dist-info/entry_points.txt
brady_django_template-0.1.4.dist-info/top_level.txt
brady_django_template-0.1.4.dist-info/RECORD
