Metadata-Version: 2.1
Name: brady-django-template
Version: 0.1.4
Summary: A tool to create Django projects with a custom template.
Home-page: https://github.com/KyawKoKoTun/brady-django-template
Author: Kyaw Ko Ko Tun
Author-email: kyawkokotunmm475157@gmail.com
License: MIT
License-File: LICENSE
Requires-Dist: Django
